claude_co/__init__.py
claude_co/__main__.py
claude_co/cli.py
claude_co/client.py
claude_co/server.py
claude_co-0.2.1.dist-info/METADATA
claude_co-0.2.1.dist-info/WHEEL
claude_co-0.2.1.dist-info/entry_points.txt
claude_co-0.2.1.dist-info/RECORD
